LICENSE
MANIFEST.in
README.md
requirements.txt
setup.cfg
setup.py
test-requirements.txt
email_normalizer/__init__.py
email_normalizer/base.py
email_normalizer/default.py
email_normalizer/fastmail.py
email_normalizer/google.py
email_normalizer/microsoft.py
email_normalizer/rambler.py
email_normalizer/yahoo.py
email_normalizer/yandex.py
python_email_normalizer.egg-info/PKG-INFO
python_email_normalizer.egg-info/SOURCES.txt
python_email_normalizer.egg-info/dependency_links.txt
python_email_normalizer.egg-info/top_level.txt