Metadata-Version: 1.1
Name: python-email-normalizer
Version: 0.1.3
Summary: Normalize email addresses
Home-page: https://github.com/r-dmv/python-email-normalizer
Author: Rubtsov Dmitry
Author-email: rubtsov.dmv@gmail.com
License: The MIT License (MIT)
